tbase_post/0001_initial.py
tbase_post/__init__.py
tbase_post/admin.py
tbase_post/apps.py
tbase_post/models.py
tbase_post/sitemaps.py
tbase_post/tests.py
tbase_post/urls.py
tbase_post/views.py
tbase_post/migrations/0001_initial.py
tbase_post/migrations/__init__.py
tbase_post/static/images/photo-1578707399887-e6d183c9e598.jpeg
tbase_post/static/images/photo-1578707399887-e6d183c9e598.jpeg:Zone.Identifier
tbase_post/templates/post_list.html
tbase_post/templates/sitemap.xml
tbase_post/templates/post/article_list_by_tag.html
tbase_post/templates/post/blog_index.html
tbase_post/templates/post/detail.html
tbase_post/templates/post/last_index.html
tbase_post/templates/post/prompt_task_detail copy.html
tbase_post/templates/post/prompt_task_detail.html
tbase_post/templates/post/prompt_task_list.html
tbase_post/templates/post/prompt_task_post_detail.html
tbase_post/templates/post/prompt_task_post_list.html
tbase_post/templates/post/extras/amazon_ads.html
tbase_post/templates/post/extras/amazon_link.html
tbase_post/templates/post/extras/get_previous_next_by_pk.html
tbase_post/templates/post/extras/hitcount_lowest_post.html
tbase_post/templates/post/extras/hitcount_top_post.html
tbase_post/templates/post/extras/last_update.html
tbase_post/templates/post/extras/related_post_by_tags.html
tbase_post/templates/post/extras/related_post_by_tags_mini.html
tbase_post/templates/post/extras/seo_top_links.html
tbase_post/templates/post/extras/tags.html
tbase_post/templates/post/extras/templ.html
tbase_post/templates/post/extras/youtube_player.html
tbase_post/templatetags/__init__.py
tbase_post/templatetags/post_extras.py
django_tbase_post_product-2025.5.1617473302.dist-info/METADATA
django_tbase_post_product-2025.5.1617473302.dist-info/WHEEL
django_tbase_post_product-2025.5.1617473302.dist-info/top_level.txt
django_tbase_post_product-2025.5.1617473302.dist-info/RECORD
