Metadata-Version: 2.1
Name: django_tbase_post_product
Version: 2025.5.1617473302
Summary: Terry django base post ,
Home-page: https://terrychanorg.jetbrains.space/p/django-expand/repositories/tbase_post_product/files/README.md
Author: Terry Chan
Author-email: napoler2008@gmail.com
Requires-Dist: django-tbase-theme-tailwind>=2023.5.2116846028
Requires-Dist: django-taggit==3.0.0
Requires-Dist: martor==1.6.19
